{
  "users": [
    {
      "id": 1,
      "name": "newer",
      "age": 76
    },
    {
      "name": "new user",
      "age": 1,
      "id": 2
    },
    {
      "name": "Graziela",
      "age": 65,
      "id": 3
    },
    {
      "name": "Graziela",
      "age": 65,
      "id": 4
    },
    {
      "name": "Graziela",
      "age": 65,
      "id": 5
    },
    {
      "name": "Graziela",
      "age": 65,
      "id": 6
    },
    {
      "name": "Graziela",
      "age": 65,
      "id": 7
    },
    {
      "name": "Teste",
      "age": 65,
      "id": 8
    },
    {
      "name": "Teste",
      "age": 49,
      "id": 9
    }
  ]
}